Comparator/comparator.v
// Program to implement a 4-bit comparator using Verilog

module comparator (A,B, G,E,L);
    input wire [3:0] A, B;
    output reg G, E, L;
    always @(*)
    begin
        if(A>B)
        begin
            G=1; E=0; L=0;
        end
        else if(A==B)
        begin
            G=0; E=1; L=0;
        end
        else
        begin
            G=0; E=0; L=1;
        end
    end
endmodule

Comparator/tb_comparator.v
`timescale 1ps/1ps
module testbench;
    reg[3:0] A,B;
    wire G,E,L;

    comparator uut(                       //uut is the instance name <unit under test>
        .A(A), .B(B), .G(G), .E(E), .L(L)
    );
    initial begin
        $dumpfile("comparator_output.vcd");
        $dumpvars(0, testbench);

        // Test Cases

        // 1. A < B Cases
        A = 4'b0000; B = 4'b0001; #10;
        A = 4'b0010; B = 4'b1000; #10;
        A = 4'b0100; B = 4'b1100; #10;

        // 2. A > B Cases
        A = 4'b1000; B = 4'b0110; #10;
        A = 4'b1101; B = 4'b1010; #10;
        A = 4'b1111; B = 4'b0111; #10;

        // 3. A == B Cases
        A = 4'b0000; B = 4'b0000; #10;
        A = 4'b0101; B = 4'b0101; #10;
        A = 4'b1111; B = 4'b1111; #10;

        // 4. Edge Cases
        A = 4'b0000; B = 4'b1111; #10;  // Min vs Max
        A = 4'b1111; B = 4'b0000; #10;  // Max vs Min

        $finish;
    end
    
endmodule

Comparator/comparator_output.vcd
$date
	Fri Mar 07 02:57:30 2025
$end
$version
	Icarus Verilog
$end
$timescale
	1ps
$end
$scope module testbench $end
$var wire 1 ! L $end
$var wire 1 " G $end
$var wire 1 # E $end
$var reg 4 $ A [3:0] $end
$var reg 4 % B [3:0] $end
$scope module uut $end
$var wire 4 & A [3:0] $end
$var wire 4 ' B [3:0] $end
$var reg 1 # E $end
$var reg 1 " G $end
$var reg 1 ! L $end
$upscope $end
$upscope $end
$enddefinitions $end
$comment Show the parameter values. $end
$dumpall
$end
#0
$dumpvars
b1 '
b0 &
b1 %
b0 $
0#
0"
1!
$end
#10
b1000 %
b1000 '
b10 $
b10 &
#20
b1100 %
b1100 '
b100 $
b100 &
#30
0!
1"
b110 %
b110 '
b1000 $
b1000 &
#40
b1010 %
b1010 '
b1101 $
b1101 &
#50
b111 %
b111 '
b1111 $
b1111 &
#60
1#
0"
b0 %
b0 '
b0 $
b0 &
#70
b101 %
b101 '
b101 $
b101 &
#80
b1111 %
b1111 '
b1111 $
b1111 &
#90
1!
0#
b0 $
b0 &
#100
0!
1"
b0 %
b0 '
b1111 $
b1111 &
